flaskoidc/__init__.py
flaskoidc/config.py
flaskoidc/models.py
flaskoidc-1.1.2.dist-info/LICENSE
flaskoidc-1.1.2.dist-info/METADATA
flaskoidc-1.1.2.dist-info/WHEEL
flaskoidc-1.1.2.dist-info/top_level.txt
flaskoidc-1.1.2.dist-info/RECORD
