Metadata-Version: 2.1
Name: flaskoidc
Version: 1.1.2
Summary: Flask wrapper with pre-configured OAuth2 and OIDC support
Home-page: https://github.com/verdan/flaskoidc.git
Author: Verdan Mahmood
Author-email: verdan.mahmood@gmail.com
License: UNKNOWN
Platform: UNKNOWN
Requires-Python: >=3.6
License-File: LICENSE
Requires-Dist: Flask (>=1.0.2)
Requires-Dist: Authlib (<2.0.0,>=1.0.0)
Requires-Dist: requests (>=2.25.1)
Requires-Dist: Flask-SQLAlchemy (>=2.5.1)
